{"version":"0.0.0","commands":{"create":{"id":"create","description":"Create a new Pizza","pluginName":"pizza-cli","pluginType":"core","aliases":[],"examples":["$ pizza create\nYour pizza is ready!\n"],"flags":{"help":{"name":"help","type":"boolean","char":"h","description":"show CLI help","allowNo":false},"crust":{"name":"crust","type":"option","char":"c","description":"Type of Crust (Thin/Thick)"},"toppings":{"name":"toppings","type":"option","char":"t","description":"Toppings to add","options":["pepperoni","mushroom","bacon","pineapple"]},"extraSauce":{"name":"extraSauce","type":"boolean","char":"x","description":"Do you want extra sauce?","allowNo":false}},"args":[{"name":"count","description":"How many pizza you want to create","required":false,"default":null}]}}}